wg_finutils/__init__.py
wg_finutils/ChildSupportObligations.py
wg_finutils/FinanceObject.py
wg_finutils/financeutils.py
wg_finutils/nm-cs-support.txt
wg_finutils/utilityclasses.py
wg_finutils-0.1.2.dist-info/WHEEL
wg_finutils-0.1.2.dist-info/METADATA
wg_finutils-0.1.2.dist-info/RECORD
