Metadata-Version: 2.1
Name: wg-finutils
Version: 0.1.2
Summary: 
Author: will george
Author-email: wrgeorge1983@gmail.com
Requires-Python: >=3.7,<4.0
Classifier: Programming Language :: Python :: 3
Classifier: Programming Language :: Python :: 3.7
Classifier: Programming Language :: Python :: 3.8
Classifier: Programming Language :: Python :: 3.9
Requires-Dist: click (>=7.1.2,<8.0.0)
